{
  "text": "If any man or woman that believeth have widows, let them relieve them, and let not the church be charged; that it may relieve them that are widows indeed.",
  "words": [
    {
      "position": 1,
      "text": "If",
      "lemma": "strong:G1487 lemma.TR:ει",
      "morph": "robinson:COND",
      "strongs": [
        "G1487"
      ],
      "metadata": {
        "src": "1"
      },
      "gematria": {
        "standard": 15,
        "ordinal": 3,
        "reduced": 15
      }
    },
    {
      "position": 2,
      "text": "any",
      "lemma": "strong:G5100 lemma.TR:τις",
      "morph": "robinson:X-NSM",
      "strongs": [
        "G5100"
      ],
      "metadata": {
        "src": "2"
      },
      "gematria": {
        "standard": 40,
        "ordinal": 6,
        "reduced": 13
      }
    },
    {
      "position": 3,
      "text": "man",
      "lemma": "strong:G4103 lemma.TR:πιστος",
      "morph": "robinson:A-NSM",
      "strongs": [
        "G4103"
      ],
      "metadata": {
        "src": "3",
        "type": "x-split-3227"
      },
      "gematria": {
        "standard": 28,
        "ordinal": 6,
        "reduced": 10
      }
    },
    {
      "position": 4,
      "text": "or",
      "lemma": "strong:G2228 lemma.TR:η",
      "morph": "robinson:PRT",
      "strongs": [
        "G2228"
      ],
      "metadata": {
        "src": "4"
      },
      "gematria": {
        "standard": 33,
        "ordinal": 3,
        "reduced": 15
      }
    },
    {
      "position": 5,
      "text": "woman",
      "lemma": "strong:G4103 lemma.TR:πιστη",
      "morph": "robinson:A-NSF",
      "strongs": [
        "G4103"
      ],
      "metadata": {
        "src": "5"
      },
      "gematria": {
        "standard": 66,
        "ordinal": 15,
        "reduced": 21
      }
    },
    {
      "position": 6,
      "text": "that",
      "lemma": "strong:G4103 lemma.TR:πιστος",
      "morph": "robinson:A-NSM",
      "strongs": [
        "G4103"
      ],
      "metadata": {
        "src": "3",
        "type": "x-split-3227"
      },
      "gematria": {
        "standard": 49,
        "ordinal": 10,
        "reduced": 13
      }
    },
    {
      "position": 7,
      "text": "believeth",
      "lemma": "strong:G4103 lemma.TR:πιστος",
      "morph": "robinson:A-NSM",
      "strongs": [
        "G4103"
      ],
      "metadata": {
        "src": "3",
        "type": "x-split-3227"
      },
      "gematria": {
        "standard": 88,
        "ordinal": 45,
        "reduced": 43
      }
    },
    {
      "position": 8,
      "text": "have",
      "lemma": "strong:G2192 lemma.TR:εχει",
      "morph": "robinson:V-PAI-3S",
      "strongs": [
        "G2192"
      ],
      "metadata": {
        "src": "6"
      },
      "gematria": {
        "standard": 36,
        "ordinal": 10,
        "reduced": 18
      }
    },
    {
      "position": 9,
      "text": "widows,",
      "lemma": "strong:G5503 lemma.TR:χηρας",
      "morph": "robinson:N-APF",
      "strongs": [
        "G5503"
      ],
      "metadata": {
        "src": "7"
      },
      "gematria": {
        "standard": 93,
        "ordinal": 21,
        "reduced": 30
      }
    },
    {
      "position": 10,
      "text": "let",
      "lemma": "strong:G1884 lemma.TR:επαρκειτω",
      "morph": "robinson:V-PAM-3S",
      "strongs": [
        "G1884"
      ],
      "metadata": {
        "src": "8"
      },
      "gematria": {
        "standard": 37,
        "ordinal": 6,
        "reduced": 10
      }
    },
    {
      "position": 11,
      "text": "them",
      "lemma": "strong:G1884 lemma.TR:επαρκειτω",
      "morph": "robinson:V-PAM-3S",
      "strongs": [
        "G1884"
      ],
      "metadata": {
        "src": "8"
      },
      "gematria": {
        "standard": 46,
        "ordinal": 10,
        "reduced": 19
      }
    },
    {
      "position": 12,
      "text": "relieve",
      "lemma": "strong:G1884 lemma.TR:επαρκειτω",
      "morph": "robinson:V-PAM-3S",
      "strongs": [
        "G1884"
      ],
      "metadata": {
        "src": "8"
      },
      "gematria": {
        "standard": 76,
        "ordinal": 28,
        "reduced": 40
      }
    },
    {
      "position": 13,
      "text": "them,",
      "lemma": "strong:G846 lemma.TR:αυταις",
      "morph": "robinson:P-DPF",
      "strongs": [
        "G846"
      ],
      "metadata": {
        "src": "9"
      },
      "gematria": {
        "standard": 46,
        "ordinal": 10,
        "reduced": 19
      }
    },
    {
      "position": 14,
      "text": "and",
      "lemma": "strong:G2532 lemma.TR:και",
      "morph": "robinson:CONJ",
      "strongs": [
        "G2532"
      ],
      "metadata": {
        "src": "10"
      },
      "gematria": {
        "standard": 19,
        "ordinal": 6,
        "reduced": 10
      }
    },
    {
      "position": 15,
      "text": "let",
      "lemma": "strong:G916 lemma.TR:βαρεισθω",
      "morph": "robinson:V-PPM-3S",
      "strongs": [
        "G916"
      ],
      "metadata": {
        "src": "12",
        "type": "x-split-3228"
      },
      "gematria": {
        "standard": 37,
        "ordinal": 6,
        "reduced": 10
      }
    },
    {
      "position": 16,
      "text": "not",
      "lemma": "strong:G3361 lemma.TR:μη",
      "morph": "robinson:PRT-N",
      "strongs": [
        "G3361"
      ],
      "metadata": {
        "src": "11"
      },
      "gematria": {
        "standard": 49,
        "ordinal": 6,
        "reduced": 13
      }
    },
    {
      "position": 17,
      "text": "the",
      "lemma": "strong:G3588 strong:G1577 lemma.TR:η lemma.TR:εκκλησια",
      "morph": "robinson:T-NSF robinson:N-NSF",
      "strongs": [
        "G3588",
        "G1577"
      ],
      "metadata": {
        "src": "13 14"
      },
      "gematria": {
        "standard": 33,
        "ordinal": 6,
        "reduced": 15
      }
    },
    {
      "position": 18,
      "text": "church",
      "lemma": "strong:G3588 strong:G1577 lemma.TR:η lemma.TR:εκκλησια",
      "morph": "robinson:T-NSF robinson:N-NSF",
      "strongs": [
        "G3588",
        "G1577"
      ],
      "metadata": {
        "src": "13 14"
      },
      "gematria": {
        "standard": 61,
        "ordinal": 21,
        "reduced": 34
      }
    },
    {
      "position": 19,
      "text": "be",
      "lemma": "strong:G916 lemma.TR:βαρεισθω",
      "morph": "robinson:V-PPM-3S",
      "strongs": [
        "G916"
      ],
      "metadata": {
        "src": "12",
        "type": "x-split-3228"
      },
      "gematria": {
        "standard": 7,
        "ordinal": 3,
        "reduced": 7
      }
    },
    {
      "position": 20,
      "text": "charged;",
      "lemma": "strong:G916 lemma.TR:βαρεισθω",
      "morph": "robinson:V-PPM-3S",
      "strongs": [
        "G916"
      ],
      "metadata": {
        "src": "12",
        "type": "x-split-3228"
      },
      "gematria": {
        "standard": 46,
        "ordinal": 28,
        "reduced": 37
      }
    },
    {
      "position": 21,
      "text": "that",
      "lemma": "strong:G2443 lemma.TR:ινα",
      "morph": "robinson:CONJ",
      "strongs": [
        "G2443"
      ],
      "metadata": {
        "src": "15"
      },
      "gematria": {
        "standard": 49,
        "ordinal": 10,
        "reduced": 13
      }
    },
    {
      "position": 22,
      "text": "it",
      "lemma": "strong:G1884 lemma.TR:επαρκεση",
      "morph": "robinson:V-AAS-3S",
      "strongs": [
        "G1884"
      ],
      "metadata": {
        "src": "19"
      },
      "gematria": {
        "standard": 29,
        "ordinal": 3,
        "reduced": 11
      }
    },
    {
      "position": 23,
      "text": "may",
      "lemma": "strong:G1884 lemma.TR:επαρκεση",
      "morph": "robinson:V-AAS-3S",
      "strongs": [
        "G1884"
      ],
      "metadata": {
        "src": "19"
      },
      "gematria": {
        "standard": 39,
        "ordinal": 6,
        "reduced": 12
      }
    },
    {
      "position": 24,
      "text": "relieve",
      "lemma": "strong:G1884 lemma.TR:επαρκεση",
      "morph": "robinson:V-AAS-3S",
      "strongs": [
        "G1884"
      ],
      "metadata": {
        "src": "19"
      },
      "gematria": {
        "standard": 76,
        "ordinal": 28,
        "reduced": 40
      }
    },
    {
      "position": 25,
      "text": "them",
      "lemma": "strong:G3588 lemma.TR:ταις",
      "morph": "robinson:T-DPF",
      "strongs": [
        "G3588"
      ],
      "metadata": {
        "src": "16"
      },
      "gematria": {
        "standard": 46,
        "ordinal": 10,
        "reduced": 19
      }
    },
    {
      "position": 26,
      "text": "that",
      "lemma": "strong:G3588 lemma.TR:ταις",
      "morph": "robinson:T-DPF",
      "strongs": [
        "G3588"
      ],
      "metadata": {
        "src": "16"
      },
      "gematria": {
        "standard": 49,
        "ordinal": 10,
        "reduced": 13
      }
    },
    {
      "position": 27,
      "text": "are",
      "lemma": "strong:G3689 lemma.TR:οντως",
      "morph": "robinson:ADV",
      "strongs": [
        "G3689"
      ],
      "metadata": {
        "src": "17",
        "type": "x-split-3229"
      },
      "gematria": {
        "standard": 24,
        "ordinal": 6,
        "reduced": 15
      }
    },
    {
      "position": 28,
      "text": "widows",
      "lemma": "strong:G5503 lemma.TR:χηραις",
      "morph": "robinson:N-DPF",
      "strongs": [
        "G5503"
      ],
      "metadata": {
        "src": "18"
      },
      "gematria": {
        "standard": 93,
        "ordinal": 21,
        "reduced": 30
      }
    },
    {
      "position": 29,
      "text": "indeed.",
      "lemma": "strong:G3689 lemma.TR:οντως",
      "morph": "robinson:ADV",
      "strongs": [
        "G3689"
      ],
      "metadata": {
        "src": "17",
        "type": "x-split-3229"
      },
      "gematria": {
        "standard": 41,
        "ordinal": 21,
        "reduced": 32
      }
    }
  ],
  "gematria": {
    "standard": 1351,
    "ordinal": 364,
    "reduced": 577
  }
}