{
  "text": "They did work wilily, and went and made as if they had been ambassadors, and took old sacks upon their asses, and wine bottles, old, and rent, and bound up;",
  "words": [
    {
      "position": 1,
      "text": "They",
      "lemma": "strong:H06213",
      "morph": "strongMorph:TH8799",
      "strongs": [
        "H6213"
      ],
      "gematria": {
        "standard": 58,
        "ordinal": 58,
        "reduced": 4
      }
    },
    {
      "position": 2,
      "text": "did",
      "lemma": "strong:H06213",
      "morph": "strongMorph:TH8799",
      "strongs": [
        "H6213"
      ],
      "gematria": {
        "standard": 17,
        "ordinal": 17,
        "reduced": 8
      }
    },
    {
      "position": 3,
      "text": "work",
      "lemma": "strong:H06213",
      "morph": "strongMorph:TH8799",
      "strongs": [
        "H6213"
      ],
      "gematria": {
        "standard": 67,
        "ordinal": 67,
        "reduced": 4
      }
    },
    {
      "position": 4,
      "text": "wilily,",
      "lemma": "strong:H06195",
      "morph": null,
      "strongs": [
        "H6195"
      ],
      "gematria": {
        "standard": 90,
        "ordinal": 90,
        "reduced": 9
      }
    },
    {
      "position": 5,
      "text": "and",
      "lemma": "strong:H03212",
      "morph": "strongMorph:TH8799",
      "strongs": [
        "H3212"
      ],
      "gematria": {
        "standard": 19,
        "ordinal": 19,
        "reduced": 1
      }
    },
    {
      "position": 6,
      "text": "went",
      "lemma": "strong:H03212",
      "morph": "strongMorph:TH8799",
      "strongs": [
        "H3212"
      ],
      "gematria": {
        "standard": 62,
        "ordinal": 62,
        "reduced": 8
      }
    },
    {
      "position": 7,
      "text": "and",
      "lemma": "strong:H06737",
      "morph": "strongMorph:TH8691",
      "strongs": [
        "H6737"
      ],
      "gematria": {
        "standard": 19,
        "ordinal": 19,
        "reduced": 1
      }
    },
    {
      "position": 8,
      "text": "made",
      "lemma": "strong:H06737",
      "morph": "strongMorph:TH8691",
      "strongs": [
        "H6737"
      ],
      "gematria": {
        "standard": 23,
        "ordinal": 23,
        "reduced": 5
      }
    },
    {
      "position": 9,
      "text": "as",
      "lemma": "strong:H06737",
      "morph": "strongMorph:TH8691",
      "strongs": [
        "H6737"
      ],
      "gematria": {
        "standard": 20,
        "ordinal": 20,
        "reduced": 2
      }
    },
    {
      "position": 10,
      "text": "if",
      "lemma": "strong:H06737",
      "morph": "strongMorph:TH8691",
      "strongs": [
        "H6737"
      ],
      "gematria": {
        "standard": 15,
        "ordinal": 15,
        "reduced": 6
      }
    },
    {
      "position": 11,
      "text": "they",
      "lemma": "strong:H06737",
      "morph": "strongMorph:TH8691",
      "strongs": [
        "H6737"
      ],
      "gematria": {
        "standard": 58,
        "ordinal": 58,
        "reduced": 4
      }
    },
    {
      "position": 12,
      "text": "had",
      "lemma": "strong:H06737",
      "morph": "strongMorph:TH8691",
      "strongs": [
        "H6737"
      ],
      "gematria": {
        "standard": 13,
        "ordinal": 13,
        "reduced": 4
      }
    },
    {
      "position": 13,
      "text": "been",
      "lemma": "strong:H06737",
      "morph": "strongMorph:TH8691",
      "strongs": [
        "H6737"
      ],
      "gematria": {
        "standard": 26,
        "ordinal": 26,
        "reduced": 8
      }
    },
    {
      "position": 14,
      "text": "ambassadors,",
      "lemma": "strong:H06737",
      "morph": "strongMorph:TH8691",
      "strongs": [
        "H6737"
      ],
      "gematria": {
        "standard": 112,
        "ordinal": 112,
        "reduced": 4
      }
    },
    {
      "position": 15,
      "text": "and",
      "lemma": "strong:H03947",
      "morph": "strongMorph:TH8799",
      "strongs": [
        "H3947"
      ],
      "gematria": {
        "standard": 19,
        "ordinal": 19,
        "reduced": 1
      }
    },
    {
      "position": 16,
      "text": "took",
      "lemma": "strong:H03947",
      "morph": "strongMorph:TH8799",
      "strongs": [
        "H3947"
      ],
      "gematria": {
        "standard": 61,
        "ordinal": 61,
        "reduced": 7
      }
    },
    {
      "position": 17,
      "text": "old",
      "lemma": "strong:H01087",
      "morph": null,
      "strongs": [
        "H1087"
      ],
      "gematria": {
        "standard": 31,
        "ordinal": 31,
        "reduced": 4
      }
    },
    {
      "position": 18,
      "text": "sacks",
      "lemma": "strong:H08242",
      "morph": null,
      "strongs": [
        "H8242"
      ],
      "gematria": {
        "standard": 53,
        "ordinal": 53,
        "reduced": 8
      }
    },
    {
      "position": 19,
      "text": "upon",
      "lemma": "strong:H02543",
      "morph": null,
      "strongs": [
        "H2543"
      ],
      "gematria": {
        "standard": 66,
        "ordinal": 66,
        "reduced": 3
      }
    },
    {
      "position": 20,
      "text": "their",
      "lemma": "strong:H02543",
      "morph": null,
      "strongs": [
        "H2543"
      ],
      "gematria": {
        "standard": 60,
        "ordinal": 60,
        "reduced": 6
      }
    },
    {
      "position": 21,
      "text": "asses,",
      "lemma": "strong:H02543",
      "morph": null,
      "strongs": [
        "H2543"
      ],
      "gematria": {
        "standard": 63,
        "ordinal": 63,
        "reduced": 9
      }
    },
    {
      "position": 22,
      "text": "and",
      "lemma": "strong:H03196",
      "morph": null,
      "strongs": [
        "H3196"
      ],
      "gematria": {
        "standard": 19,
        "ordinal": 19,
        "reduced": 1
      }
    },
    {
      "position": 23,
      "text": "wine",
      "lemma": "strong:H03196",
      "morph": null,
      "strongs": [
        "H3196"
      ],
      "gematria": {
        "standard": 51,
        "ordinal": 51,
        "reduced": 6
      }
    },
    {
      "position": 24,
      "text": "bottles,",
      "lemma": "strong:H04997",
      "morph": null,
      "strongs": [
        "H4997"
      ],
      "gematria": {
        "standard": 93,
        "ordinal": 93,
        "reduced": 3
      }
    },
    {
      "position": 25,
      "text": "old,",
      "lemma": "strong:H01087",
      "morph": null,
      "strongs": [
        "H1087"
      ],
      "gematria": {
        "standard": 31,
        "ordinal": 31,
        "reduced": 4
      }
    },
    {
      "position": 26,
      "text": "and",
      "lemma": "strong:H01234",
      "morph": "strongMorph:TH8794",
      "strongs": [
        "H1234"
      ],
      "gematria": {
        "standard": 19,
        "ordinal": 19,
        "reduced": 1
      }
    },
    {
      "position": 27,
      "text": "rent,",
      "lemma": "strong:H01234",
      "morph": "strongMorph:TH8794",
      "strongs": [
        "H1234"
      ],
      "gematria": {
        "standard": 57,
        "ordinal": 57,
        "reduced": 3
      }
    },
    {
      "position": 28,
      "text": "and",
      "lemma": "strong:H06887",
      "morph": "strongMorph:TH8794",
      "strongs": [
        "H6887"
      ],
      "gematria": {
        "standard": 19,
        "ordinal": 19,
        "reduced": 1
      }
    },
    {
      "position": 29,
      "text": "bound",
      "lemma": "strong:H06887",
      "morph": "strongMorph:TH8794",
      "strongs": [
        "H6887"
      ],
      "gematria": {
        "standard": 56,
        "ordinal": 56,
        "reduced": 2
      }
    },
    {
      "position": 30,
      "text": "up;",
      "lemma": "strong:H06887",
      "morph": "strongMorph:TH8794",
      "strongs": [
        "H6887"
      ],
      "gematria": {
        "standard": 37,
        "ordinal": 37,
        "reduced": 1
      }
    }
  ],
  "gematria": {
    "standard": 1334,
    "ordinal": 1334,
    "reduced": 128
  }
}