{
  "text": "Thus saith the Lord of hosts; If thou wilt walk in my ways, and if thou wilt keep my charge, then thou shalt also judge my house, and shalt also keep my courts, and I will give thee places to walk among these that stand by.",
  "words": [
    {
      "position": 1,
      "text": "Thus",
      "lemma": "strong:H0559",
      "morph": "strongMorph:TH8804",
      "strongs": [
        "H559"
      ],
      "source": {
        "lemma": "strong:H0559",
        "morph": "strongMorph:TH8804",
        "attrs": {
          "morph": "strongMorph:TH8804",
          "lemma": "strong:H0559"
        }
      }
    },
    {
      "position": 2,
      "text": "saith",
      "lemma": "strong:H0559",
      "morph": "strongMorph:TH8804",
      "strongs": [
        "H559"
      ],
      "source": {
        "lemma": "strong:H0559",
        "morph": "strongMorph:TH8804",
        "attrs": {
          "morph": "strongMorph:TH8804",
          "lemma": "strong:H0559"
        }
      }
    },
    {
      "position": 3,
      "text": "the",
      "lemma": "strong:H03068",
      "morph": null,
      "strongs": [
        "H3068"
      ],
      "source": {
        "lemma": "strong:H03068",
        "attrs": {
          "lemma": "strong:H03068"
        }
      }
    },
    {
      "position": 4,
      "text": "Lord",
      "lemma": "strong:H03068",
      "morph": null,
      "strongs": [
        "H3068"
      ],
      "source": {
        "lemma": "strong:H03068",
        "attrs": {
          "lemma": "strong:H03068"
        }
      }
    },
    {
      "position": 5,
      "text": "of",
      "lemma": "strong:H06635",
      "morph": null,
      "strongs": [
        "H6635"
      ],
      "source": {
        "lemma": "strong:H06635",
        "attrs": {
          "lemma": "strong:H06635"
        }
      }
    },
    {
      "position": 6,
      "text": "hosts;",
      "lemma": "strong:H06635",
      "morph": null,
      "strongs": [
        "H6635"
      ],
      "source": {
        "lemma": "strong:H06635",
        "attrs": {
          "lemma": "strong:H06635"
        }
      }
    },
    {
      "position": 7,
      "text": "If",
      "lemma": "strong:H03212",
      "morph": "strongMorph:TH8799",
      "strongs": [
        "H3212"
      ],
      "source": {
        "lemma": "strong:H03212",
        "morph": "strongMorph:TH8799",
        "attrs": {
          "morph": "strongMorph:TH8799",
          "lemma": "strong:H03212"
        }
      }
    },
    {
      "position": 8,
      "text": "thou",
      "lemma": "strong:H03212",
      "morph": "strongMorph:TH8799",
      "strongs": [
        "H3212"
      ],
      "source": {
        "lemma": "strong:H03212",
        "morph": "strongMorph:TH8799",
        "attrs": {
          "morph": "strongMorph:TH8799",
          "lemma": "strong:H03212"
        }
      }
    },
    {
      "position": 9,
      "text": "wilt",
      "lemma": "strong:H03212",
      "morph": "strongMorph:TH8799",
      "strongs": [
        "H3212"
      ],
      "source": {
        "lemma": "strong:H03212",
        "morph": "strongMorph:TH8799",
        "attrs": {
          "morph": "strongMorph:TH8799",
          "lemma": "strong:H03212"
        }
      }
    },
    {
      "position": 10,
      "text": "walk",
      "lemma": "strong:H03212",
      "morph": "strongMorph:TH8799",
      "strongs": [
        "H3212"
      ],
      "source": {
        "lemma": "strong:H03212",
        "morph": "strongMorph:TH8799",
        "attrs": {
          "morph": "strongMorph:TH8799",
          "lemma": "strong:H03212"
        }
      }
    },
    {
      "position": 11,
      "text": "in",
      "lemma": "strong:H01870",
      "morph": null,
      "strongs": [
        "H1870"
      ],
      "source": {
        "lemma": "strong:H01870",
        "attrs": {
          "lemma": "strong:H01870"
        }
      }
    },
    {
      "position": 12,
      "text": "my",
      "lemma": "strong:H01870",
      "morph": null,
      "strongs": [
        "H1870"
      ],
      "source": {
        "lemma": "strong:H01870",
        "attrs": {
          "lemma": "strong:H01870"
        }
      }
    },
    {
      "position": 13,
      "text": "ways,",
      "lemma": "strong:H01870",
      "morph": null,
      "strongs": [
        "H1870"
      ],
      "source": {
        "lemma": "strong:H01870",
        "attrs": {
          "lemma": "strong:H01870"
        }
      }
    },
    {
      "position": 14,
      "text": "and",
      "lemma": "strong:H08104",
      "morph": "strongMorph:TH8799",
      "strongs": [
        "H8104"
      ],
      "source": {
        "lemma": "strong:H08104",
        "morph": "strongMorph:TH8799",
        "attrs": {
          "morph": "strongMorph:TH8799",
          "lemma": "strong:H08104"
        }
      }
    },
    {
      "position": 15,
      "text": "if",
      "lemma": "strong:H08104",
      "morph": "strongMorph:TH8799",
      "strongs": [
        "H8104"
      ],
      "source": {
        "lemma": "strong:H08104",
        "morph": "strongMorph:TH8799",
        "attrs": {
          "morph": "strongMorph:TH8799",
          "lemma": "strong:H08104"
        }
      }
    },
    {
      "position": 16,
      "text": "thou",
      "lemma": "strong:H08104",
      "morph": "strongMorph:TH8799",
      "strongs": [
        "H8104"
      ],
      "source": {
        "lemma": "strong:H08104",
        "morph": "strongMorph:TH8799",
        "attrs": {
          "morph": "strongMorph:TH8799",
          "lemma": "strong:H08104"
        }
      }
    },
    {
      "position": 17,
      "text": "wilt",
      "lemma": "strong:H08104",
      "morph": "strongMorph:TH8799",
      "strongs": [
        "H8104"
      ],
      "source": {
        "lemma": "strong:H08104",
        "morph": "strongMorph:TH8799",
        "attrs": {
          "morph": "strongMorph:TH8799",
          "lemma": "strong:H08104"
        }
      }
    },
    {
      "position": 18,
      "text": "keep",
      "lemma": "strong:H08104",
      "morph": "strongMorph:TH8799",
      "strongs": [
        "H8104"
      ],
      "source": {
        "lemma": "strong:H08104",
        "morph": "strongMorph:TH8799",
        "attrs": {
          "morph": "strongMorph:TH8799",
          "lemma": "strong:H08104"
        }
      }
    },
    {
      "position": 19,
      "text": "my",
      "lemma": "strong:H04931",
      "morph": null,
      "strongs": [
        "H4931"
      ],
      "source": {
        "lemma": "strong:H04931",
        "attrs": {
          "lemma": "strong:H04931"
        }
      }
    },
    {
      "position": 20,
      "text": "charge,",
      "lemma": "strong:H04931",
      "morph": null,
      "strongs": [
        "H4931"
      ],
      "source": {
        "lemma": "strong:H04931",
        "attrs": {
          "lemma": "strong:H04931"
        }
      }
    },
    {
      "position": 21,
      "text": "then",
      "lemma": "strong:H01777",
      "morph": "strongMorph:TH8799",
      "strongs": [
        "H1777"
      ],
      "source": {
        "lemma": "strong:H01777",
        "morph": "strongMorph:TH8799",
        "attrs": {
          "morph": "strongMorph:TH8799",
          "lemma": "strong:H01777"
        }
      }
    },
    {
      "position": 22,
      "text": "thou",
      "lemma": "strong:H01777",
      "morph": "strongMorph:TH8799",
      "strongs": [
        "H1777"
      ],
      "source": {
        "lemma": "strong:H01777",
        "morph": "strongMorph:TH8799",
        "attrs": {
          "morph": "strongMorph:TH8799",
          "lemma": "strong:H01777"
        }
      }
    },
    {
      "position": 23,
      "text": "shalt",
      "lemma": "strong:H01777",
      "morph": "strongMorph:TH8799",
      "strongs": [
        "H1777"
      ],
      "source": {
        "lemma": "strong:H01777",
        "morph": "strongMorph:TH8799",
        "attrs": {
          "morph": "strongMorph:TH8799",
          "lemma": "strong:H01777"
        }
      }
    },
    {
      "position": 24,
      "text": "also",
      "lemma": "strong:H01777",
      "morph": "strongMorph:TH8799",
      "strongs": [
        "H1777"
      ],
      "source": {
        "lemma": "strong:H01777",
        "morph": "strongMorph:TH8799",
        "attrs": {
          "morph": "strongMorph:TH8799",
          "lemma": "strong:H01777"
        }
      }
    },
    {
      "position": 25,
      "text": "judge",
      "lemma": "strong:H01777",
      "morph": "strongMorph:TH8799",
      "strongs": [
        "H1777"
      ],
      "source": {
        "lemma": "strong:H01777",
        "morph": "strongMorph:TH8799",
        "attrs": {
          "morph": "strongMorph:TH8799",
          "lemma": "strong:H01777"
        }
      }
    },
    {
      "position": 26,
      "text": "my",
      "lemma": "strong:H01004",
      "morph": null,
      "strongs": [
        "H1004"
      ],
      "source": {
        "lemma": "strong:H01004",
        "attrs": {
          "lemma": "strong:H01004"
        }
      }
    },
    {
      "position": 27,
      "text": "house,",
      "lemma": "strong:H01004",
      "morph": null,
      "strongs": [
        "H1004"
      ],
      "source": {
        "lemma": "strong:H01004",
        "attrs": {
          "lemma": "strong:H01004"
        }
      }
    },
    {
      "position": 28,
      "text": "and",
      "lemma": "strong:H08104",
      "morph": "strongMorph:TH8799",
      "strongs": [
        "H8104"
      ],
      "source": {
        "lemma": "strong:H08104",
        "morph": "strongMorph:TH8799",
        "attrs": {
          "morph": "strongMorph:TH8799",
          "lemma": "strong:H08104"
        }
      }
    },
    {
      "position": 29,
      "text": "shalt",
      "lemma": "strong:H08104",
      "morph": "strongMorph:TH8799",
      "strongs": [
        "H8104"
      ],
      "source": {
        "lemma": "strong:H08104",
        "morph": "strongMorph:TH8799",
        "attrs": {
          "morph": "strongMorph:TH8799",
          "lemma": "strong:H08104"
        }
      }
    },
    {
      "position": 30,
      "text": "also",
      "lemma": "strong:H08104",
      "morph": "strongMorph:TH8799",
      "strongs": [
        "H8104"
      ],
      "source": {
        "lemma": "strong:H08104",
        "morph": "strongMorph:TH8799",
        "attrs": {
          "morph": "strongMorph:TH8799",
          "lemma": "strong:H08104"
        }
      }
    },
    {
      "position": 31,
      "text": "keep",
      "lemma": "strong:H08104",
      "morph": "strongMorph:TH8799",
      "strongs": [
        "H8104"
      ],
      "source": {
        "lemma": "strong:H08104",
        "morph": "strongMorph:TH8799",
        "attrs": {
          "morph": "strongMorph:TH8799",
          "lemma": "strong:H08104"
        }
      }
    },
    {
      "position": 32,
      "text": "my",
      "lemma": "strong:H02691",
      "morph": null,
      "strongs": [
        "H2691"
      ],
      "source": {
        "lemma": "strong:H02691",
        "attrs": {
          "lemma": "strong:H02691"
        }
      }
    },
    {
      "position": 33,
      "text": "courts,",
      "lemma": "strong:H02691",
      "morph": null,
      "strongs": [
        "H2691"
      ],
      "source": {
        "lemma": "strong:H02691",
        "attrs": {
          "lemma": "strong:H02691"
        }
      }
    },
    {
      "position": 34,
      "text": "and",
      "lemma": "strong:H05414",
      "morph": "strongMorph:TH8804",
      "strongs": [
        "H5414"
      ],
      "source": {
        "lemma": "strong:H05414",
        "morph": "strongMorph:TH8804",
        "attrs": {
          "morph": "strongMorph:TH8804",
          "lemma": "strong:H05414"
        }
      }
    },
    {
      "position": 35,
      "text": "I",
      "lemma": "strong:H05414",
      "morph": "strongMorph:TH8804",
      "strongs": [
        "H5414"
      ],
      "source": {
        "lemma": "strong:H05414",
        "morph": "strongMorph:TH8804",
        "attrs": {
          "morph": "strongMorph:TH8804",
          "lemma": "strong:H05414"
        }
      }
    },
    {
      "position": 36,
      "text": "will",
      "lemma": "strong:H05414",
      "morph": "strongMorph:TH8804",
      "strongs": [
        "H5414"
      ],
      "source": {
        "lemma": "strong:H05414",
        "morph": "strongMorph:TH8804",
        "attrs": {
          "morph": "strongMorph:TH8804",
          "lemma": "strong:H05414"
        }
      }
    },
    {
      "position": 37,
      "text": "give",
      "lemma": "strong:H05414",
      "morph": "strongMorph:TH8804",
      "strongs": [
        "H5414"
      ],
      "source": {
        "lemma": "strong:H05414",
        "morph": "strongMorph:TH8804",
        "attrs": {
          "morph": "strongMorph:TH8804",
          "lemma": "strong:H05414"
        }
      }
    },
    {
      "position": 38,
      "text": "thee",
      "lemma": "strong:H04108",
      "morph": "strongMorph:TH8688",
      "strongs": [
        "H4108"
      ],
      "source": {
        "lemma": "strong:H04108",
        "morph": "strongMorph:TH8688",
        "attrs": {
          "morph": "strongMorph:TH8688",
          "lemma": "strong:H04108"
        }
      }
    },
    {
      "position": 39,
      "text": "places",
      "lemma": "strong:H04108",
      "morph": "strongMorph:TH8688",
      "strongs": [
        "H4108"
      ],
      "source": {
        "lemma": "strong:H04108",
        "morph": "strongMorph:TH8688",
        "attrs": {
          "morph": "strongMorph:TH8688",
          "lemma": "strong:H04108"
        }
      }
    },
    {
      "position": 40,
      "text": "to",
      "lemma": "strong:H04108",
      "morph": "strongMorph:TH8688",
      "strongs": [
        "H4108"
      ],
      "source": {
        "lemma": "strong:H04108",
        "morph": "strongMorph:TH8688",
        "attrs": {
          "morph": "strongMorph:TH8688",
          "lemma": "strong:H04108"
        }
      }
    },
    {
      "position": 41,
      "text": "walk",
      "lemma": "strong:H04108",
      "morph": "strongMorph:TH8688",
      "strongs": [
        "H4108"
      ],
      "source": {
        "lemma": "strong:H04108",
        "morph": "strongMorph:TH8688",
        "attrs": {
          "morph": "strongMorph:TH8688",
          "lemma": "strong:H04108"
        }
      }
    },
    {
      "position": 42,
      "text": "among",
      "lemma": "strong:H05975",
      "morph": "strongMorph:TH8802",
      "strongs": [
        "H5975"
      ],
      "source": {
        "lemma": "strong:H05975",
        "morph": "strongMorph:TH8802",
        "attrs": {
          "morph": "strongMorph:TH8802",
          "lemma": "strong:H05975"
        }
      }
    },
    {
      "position": 43,
      "text": "these",
      "lemma": "strong:H05975",
      "morph": "strongMorph:TH8802",
      "strongs": [
        "H5975"
      ],
      "source": {
        "lemma": "strong:H05975",
        "morph": "strongMorph:TH8802",
        "attrs": {
          "morph": "strongMorph:TH8802",
          "lemma": "strong:H05975"
        }
      }
    },
    {
      "position": 44,
      "text": "that",
      "lemma": "strong:H05975",
      "morph": "strongMorph:TH8802",
      "strongs": [
        "H5975"
      ],
      "source": {
        "lemma": "strong:H05975",
        "morph": "strongMorph:TH8802",
        "attrs": {
          "morph": "strongMorph:TH8802",
          "lemma": "strong:H05975"
        }
      }
    },
    {
      "position": 45,
      "text": "stand",
      "lemma": "strong:H05975",
      "morph": "strongMorph:TH8802",
      "strongs": [
        "H5975"
      ],
      "source": {
        "lemma": "strong:H05975",
        "morph": "strongMorph:TH8802",
        "attrs": {
          "morph": "strongMorph:TH8802",
          "lemma": "strong:H05975"
        }
      }
    },
    {
      "position": 46,
      "text": "by.",
      "lemma": "strong:H05975",
      "morph": "strongMorph:TH8802",
      "strongs": [
        "H5975"
      ],
      "source": {
        "lemma": "strong:H05975",
        "morph": "strongMorph:TH8802",
        "attrs": {
          "morph": "strongMorph:TH8802",
          "lemma": "strong:H05975"
        }
      }
    }
  ]
}