{
  "text": "But when the flame began to arise up out of the city with a pillar of smoke, the Benjamites looked behind them, and, behold, the flame of the city ascended up to heaven.",
  "words": [
    {
      "position": 1,
      "text": "But",
      "lemma": "strong:H04864",
      "morph": null,
      "strongs": [
        "H4864"
      ],
      "source": {
        "lemma": "strong:H04864",
        "attrs": {
          "lemma": "strong:H04864"
        }
      }
    },
    {
      "position": 2,
      "text": "when",
      "lemma": "strong:H04864",
      "morph": null,
      "strongs": [
        "H4864"
      ],
      "source": {
        "lemma": "strong:H04864",
        "attrs": {
          "lemma": "strong:H04864"
        }
      }
    },
    {
      "position": 3,
      "text": "the",
      "lemma": "strong:H04864",
      "morph": null,
      "strongs": [
        "H4864"
      ],
      "source": {
        "lemma": "strong:H04864",
        "attrs": {
          "lemma": "strong:H04864"
        }
      }
    },
    {
      "position": 4,
      "text": "flame",
      "lemma": "strong:H04864",
      "morph": null,
      "strongs": [
        "H4864"
      ],
      "source": {
        "lemma": "strong:H04864",
        "attrs": {
          "lemma": "strong:H04864"
        }
      }
    },
    {
      "position": 5,
      "text": "began",
      "lemma": "strong:H02490",
      "morph": "strongMorph:TH8689",
      "strongs": [
        "H2490"
      ],
      "source": {
        "lemma": "strong:H02490",
        "morph": "strongMorph:TH8689",
        "attrs": {
          "morph": "strongMorph:TH8689",
          "lemma": "strong:H02490"
        }
      }
    },
    {
      "position": 6,
      "text": "to",
      "lemma": "strong:H05927",
      "morph": "strongMorph:TH8800",
      "strongs": [
        "H5927"
      ],
      "source": {
        "lemma": "strong:H05927",
        "morph": "strongMorph:TH8800",
        "attrs": {
          "morph": "strongMorph:TH8800",
          "lemma": "strong:H05927"
        }
      }
    },
    {
      "position": 7,
      "text": "arise",
      "lemma": "strong:H05927",
      "morph": "strongMorph:TH8800",
      "strongs": [
        "H5927"
      ],
      "source": {
        "lemma": "strong:H05927",
        "morph": "strongMorph:TH8800",
        "attrs": {
          "morph": "strongMorph:TH8800",
          "lemma": "strong:H05927"
        }
      }
    },
    {
      "position": 8,
      "text": "up",
      "lemma": "strong:H05927",
      "morph": "strongMorph:TH8800",
      "strongs": [
        "H5927"
      ],
      "source": {
        "lemma": "strong:H05927",
        "morph": "strongMorph:TH8800",
        "attrs": {
          "morph": "strongMorph:TH8800",
          "lemma": "strong:H05927"
        }
      }
    },
    {
      "position": 9,
      "text": "out",
      "lemma": "strong:H05892",
      "morph": null,
      "strongs": [
        "H5892"
      ],
      "source": {
        "lemma": "strong:H05892",
        "attrs": {
          "lemma": "strong:H05892"
        }
      }
    },
    {
      "position": 10,
      "text": "of",
      "lemma": "strong:H05892",
      "morph": null,
      "strongs": [
        "H5892"
      ],
      "source": {
        "lemma": "strong:H05892",
        "attrs": {
          "lemma": "strong:H05892"
        }
      }
    },
    {
      "position": 11,
      "text": "the",
      "lemma": "strong:H05892",
      "morph": null,
      "strongs": [
        "H5892"
      ],
      "source": {
        "lemma": "strong:H05892",
        "attrs": {
          "lemma": "strong:H05892"
        }
      }
    },
    {
      "position": 12,
      "text": "city",
      "lemma": "strong:H05892",
      "morph": null,
      "strongs": [
        "H5892"
      ],
      "source": {
        "lemma": "strong:H05892",
        "attrs": {
          "lemma": "strong:H05892"
        }
      }
    },
    {
      "position": 13,
      "text": "with",
      "lemma": "strong:H05982",
      "morph": null,
      "strongs": [
        "H5982"
      ],
      "source": {
        "lemma": "strong:H05982",
        "attrs": {
          "lemma": "strong:H05982"
        }
      }
    },
    {
      "position": 14,
      "text": "a",
      "lemma": "strong:H05982",
      "morph": null,
      "strongs": [
        "H5982"
      ],
      "source": {
        "lemma": "strong:H05982",
        "attrs": {
          "lemma": "strong:H05982"
        }
      }
    },
    {
      "position": 15,
      "text": "pillar",
      "lemma": "strong:H05982",
      "morph": null,
      "strongs": [
        "H5982"
      ],
      "source": {
        "lemma": "strong:H05982",
        "attrs": {
          "lemma": "strong:H05982"
        }
      }
    },
    {
      "position": 16,
      "text": "of",
      "lemma": "strong:H06227",
      "morph": null,
      "strongs": [
        "H6227"
      ],
      "source": {
        "lemma": "strong:H06227",
        "attrs": {
          "lemma": "strong:H06227"
        }
      }
    },
    {
      "position": 17,
      "text": "smoke,",
      "lemma": "strong:H06227",
      "morph": null,
      "strongs": [
        "H6227"
      ],
      "source": {
        "lemma": "strong:H06227",
        "attrs": {
          "lemma": "strong:H06227"
        }
      }
    },
    {
      "position": 18,
      "text": "the",
      "lemma": "strong:H01145",
      "morph": null,
      "strongs": [
        "H1145"
      ],
      "source": {
        "lemma": "strong:H01145",
        "attrs": {
          "lemma": "strong:H01145"
        }
      }
    },
    {
      "position": 19,
      "text": "Benjamites",
      "lemma": "strong:H01145",
      "morph": null,
      "strongs": [
        "H1145"
      ],
      "source": {
        "lemma": "strong:H01145",
        "attrs": {
          "lemma": "strong:H01145"
        }
      }
    },
    {
      "position": 20,
      "text": "looked",
      "lemma": "strong:H06437",
      "morph": "strongMorph:TH8799",
      "strongs": [
        "H6437"
      ],
      "source": {
        "lemma": "strong:H06437",
        "morph": "strongMorph:TH8799",
        "attrs": {
          "morph": "strongMorph:TH8799",
          "lemma": "strong:H06437"
        }
      }
    },
    {
      "position": 21,
      "text": "behind",
      "lemma": "strong:H0310",
      "morph": null,
      "strongs": [
        "H310"
      ],
      "source": {
        "lemma": "strong:H0310",
        "attrs": {
          "lemma": "strong:H0310"
        }
      }
    },
    {
      "position": 22,
      "text": "them,",
      "lemma": "strong:H03632",
      "morph": null,
      "strongs": [
        "H3632"
      ],
      "source": {
        "lemma": "strong:H03632",
        "attrs": {
          "lemma": "strong:H03632"
        }
      }
    },
    {
      "position": 23,
      "text": "and,",
      "lemma": "strong:H03632",
      "morph": null,
      "strongs": [
        "H3632"
      ],
      "source": {
        "lemma": "strong:H03632",
        "attrs": {
          "lemma": "strong:H03632"
        }
      }
    },
    {
      "position": 24,
      "text": "behold,",
      "lemma": "strong:H03632",
      "morph": null,
      "strongs": [
        "H3632"
      ],
      "source": {
        "lemma": "strong:H03632",
        "attrs": {
          "lemma": "strong:H03632"
        }
      }
    },
    {
      "position": 25,
      "text": "the",
      "lemma": "strong:H03632",
      "morph": null,
      "strongs": [
        "H3632"
      ],
      "source": {
        "lemma": "strong:H03632",
        "attrs": {
          "lemma": "strong:H03632"
        }
      }
    },
    {
      "position": 26,
      "text": "flame",
      "lemma": "strong:H03632",
      "morph": null,
      "strongs": [
        "H3632"
      ],
      "source": {
        "lemma": "strong:H03632",
        "attrs": {
          "lemma": "strong:H03632"
        }
      }
    },
    {
      "position": 27,
      "text": "of",
      "lemma": "strong:H05892",
      "morph": null,
      "strongs": [
        "H5892"
      ],
      "source": {
        "lemma": "strong:H05892",
        "attrs": {
          "lemma": "strong:H05892"
        }
      }
    },
    {
      "position": 28,
      "text": "the",
      "lemma": "strong:H05892",
      "morph": null,
      "strongs": [
        "H5892"
      ],
      "source": {
        "lemma": "strong:H05892",
        "attrs": {
          "lemma": "strong:H05892"
        }
      }
    },
    {
      "position": 29,
      "text": "city",
      "lemma": "strong:H05892",
      "morph": null,
      "strongs": [
        "H5892"
      ],
      "source": {
        "lemma": "strong:H05892",
        "attrs": {
          "lemma": "strong:H05892"
        }
      }
    },
    {
      "position": 30,
      "text": "ascended",
      "lemma": "strong:H05927",
      "morph": "strongMorph:TH8804",
      "strongs": [
        "H5927"
      ],
      "source": {
        "lemma": "strong:H05927",
        "morph": "strongMorph:TH8804",
        "attrs": {
          "morph": "strongMorph:TH8804",
          "lemma": "strong:H05927"
        }
      }
    },
    {
      "position": 31,
      "text": "up",
      "lemma": "strong:H05927",
      "morph": "strongMorph:TH8804",
      "strongs": [
        "H5927"
      ],
      "source": {
        "lemma": "strong:H05927",
        "morph": "strongMorph:TH8804",
        "attrs": {
          "morph": "strongMorph:TH8804",
          "lemma": "strong:H05927"
        }
      }
    },
    {
      "position": 32,
      "text": "to",
      "lemma": "strong:H08064",
      "morph": null,
      "strongs": [
        "H8064"
      ],
      "source": {
        "lemma": "strong:H08064",
        "attrs": {
          "lemma": "strong:H08064"
        }
      }
    },
    {
      "position": 33,
      "text": "heaven.",
      "lemma": "strong:H08064",
      "morph": null,
      "strongs": [
        "H8064"
      ],
      "source": {
        "lemma": "strong:H08064",
        "attrs": {
          "lemma": "strong:H08064"
        }
      }
    }
  ]
}