{
  "text": "Thou hast set up the right hand of his adversaries; thou hast made all his enemies to rejoice.",
  "words": [
    {
      "position": 1,
      "text": "Thou",
      "lemma": "strong:H07311",
      "morph": "strongMorph:TH8689",
      "strongs": [
        "H7311"
      ],
      "source": {
        "lemma": "strong:H07311",
        "morph": "strongMorph:TH8689",
        "attrs": {
          "morph": "strongMorph:TH8689",
          "lemma": "strong:H07311"
        }
      }
    },
    {
      "position": 2,
      "text": "hast",
      "lemma": "strong:H07311",
      "morph": "strongMorph:TH8689",
      "strongs": [
        "H7311"
      ],
      "source": {
        "lemma": "strong:H07311",
        "morph": "strongMorph:TH8689",
        "attrs": {
          "morph": "strongMorph:TH8689",
          "lemma": "strong:H07311"
        }
      }
    },
    {
      "position": 3,
      "text": "set",
      "lemma": "strong:H07311",
      "morph": "strongMorph:TH8689",
      "strongs": [
        "H7311"
      ],
      "source": {
        "lemma": "strong:H07311",
        "morph": "strongMorph:TH8689",
        "attrs": {
          "morph": "strongMorph:TH8689",
          "lemma": "strong:H07311"
        }
      }
    },
    {
      "position": 4,
      "text": "up",
      "lemma": "strong:H07311",
      "morph": "strongMorph:TH8689",
      "strongs": [
        "H7311"
      ],
      "source": {
        "lemma": "strong:H07311",
        "morph": "strongMorph:TH8689",
        "attrs": {
          "morph": "strongMorph:TH8689",
          "lemma": "strong:H07311"
        }
      }
    },
    {
      "position": 5,
      "text": "the",
      "lemma": "strong:H03225",
      "morph": null,
      "strongs": [
        "H3225"
      ],
      "source": {
        "lemma": "strong:H03225",
        "attrs": {
          "lemma": "strong:H03225"
        }
      }
    },
    {
      "position": 6,
      "text": "right",
      "lemma": "strong:H03225",
      "morph": null,
      "strongs": [
        "H3225"
      ],
      "source": {
        "lemma": "strong:H03225",
        "attrs": {
          "lemma": "strong:H03225"
        }
      }
    },
    {
      "position": 7,
      "text": "hand",
      "lemma": "strong:H03225",
      "morph": null,
      "strongs": [
        "H3225"
      ],
      "source": {
        "lemma": "strong:H03225",
        "attrs": {
          "lemma": "strong:H03225"
        }
      }
    },
    {
      "position": 8,
      "text": "of",
      "lemma": "strong:H06862",
      "morph": null,
      "strongs": [
        "H6862"
      ],
      "source": {
        "lemma": "strong:H06862",
        "attrs": {
          "lemma": "strong:H06862"
        }
      }
    },
    {
      "position": 9,
      "text": "his",
      "lemma": "strong:H06862",
      "morph": null,
      "strongs": [
        "H6862"
      ],
      "source": {
        "lemma": "strong:H06862",
        "attrs": {
          "lemma": "strong:H06862"
        }
      }
    },
    {
      "position": 10,
      "text": "adversaries;",
      "lemma": "strong:H06862",
      "morph": null,
      "strongs": [
        "H6862"
      ],
      "source": {
        "lemma": "strong:H06862",
        "attrs": {
          "lemma": "strong:H06862"
        }
      }
    },
    {
      "position": 11,
      "text": "thou",
      "lemma": "strong:H0341",
      "morph": "strongMorph:TH8802",
      "strongs": [
        "H341"
      ],
      "source": {
        "lemma": "strong:H0341",
        "morph": "strongMorph:TH8802",
        "attrs": {
          "morph": "strongMorph:TH8802",
          "lemma": "strong:H0341"
        }
      }
    },
    {
      "position": 12,
      "text": "hast",
      "lemma": "strong:H0341",
      "morph": "strongMorph:TH8802",
      "strongs": [
        "H341"
      ],
      "source": {
        "lemma": "strong:H0341",
        "morph": "strongMorph:TH8802",
        "attrs": {
          "morph": "strongMorph:TH8802",
          "lemma": "strong:H0341"
        }
      }
    },
    {
      "position": 13,
      "text": "made",
      "lemma": "strong:H0341",
      "morph": "strongMorph:TH8802",
      "strongs": [
        "H341"
      ],
      "source": {
        "lemma": "strong:H0341",
        "morph": "strongMorph:TH8802",
        "attrs": {
          "morph": "strongMorph:TH8802",
          "lemma": "strong:H0341"
        }
      }
    },
    {
      "position": 14,
      "text": "all",
      "lemma": "strong:H0341",
      "morph": "strongMorph:TH8802",
      "strongs": [
        "H341"
      ],
      "source": {
        "lemma": "strong:H0341",
        "morph": "strongMorph:TH8802",
        "attrs": {
          "morph": "strongMorph:TH8802",
          "lemma": "strong:H0341"
        }
      }
    },
    {
      "position": 15,
      "text": "his",
      "lemma": "strong:H0341",
      "morph": "strongMorph:TH8802",
      "strongs": [
        "H341"
      ],
      "source": {
        "lemma": "strong:H0341",
        "morph": "strongMorph:TH8802",
        "attrs": {
          "morph": "strongMorph:TH8802",
          "lemma": "strong:H0341"
        }
      }
    },
    {
      "position": 16,
      "text": "enemies",
      "lemma": "strong:H0341",
      "morph": "strongMorph:TH8802",
      "strongs": [
        "H341"
      ],
      "source": {
        "lemma": "strong:H0341",
        "morph": "strongMorph:TH8802",
        "attrs": {
          "morph": "strongMorph:TH8802",
          "lemma": "strong:H0341"
        }
      }
    },
    {
      "position": 17,
      "text": "to",
      "lemma": "strong:H08055",
      "morph": "strongMorph:TH8689",
      "strongs": [
        "H8055"
      ],
      "source": {
        "lemma": "strong:H08055",
        "morph": "strongMorph:TH8689",
        "attrs": {
          "morph": "strongMorph:TH8689",
          "lemma": "strong:H08055"
        }
      }
    },
    {
      "position": 18,
      "text": "rejoice.",
      "lemma": "strong:H08055",
      "morph": "strongMorph:TH8689",
      "strongs": [
        "H8055"
      ],
      "source": {
        "lemma": "strong:H08055",
        "morph": "strongMorph:TH8689",
        "attrs": {
          "morph": "strongMorph:TH8689",
          "lemma": "strong:H08055"
        }
      }
    }
  ]
}