{
  "text": "So that my bonds in Christ are manifest in all the palace, and in all other places;",
  "words": [
    {
      "position": 1,
      "text": "So",
      "lemma": "strong:G5620 lemma.TR:ωστε",
      "morph": "robinson:CONJ",
      "strongs": [
        "G5620"
      ],
      "metadata": {
        "src": "1"
      },
      "gematria": {
        "standard": 34,
        "ordinal": 3,
        "reduced": 7
      }
    },
    {
      "position": 2,
      "text": "that",
      "lemma": "strong:G5620 lemma.TR:ωστε",
      "morph": "robinson:CONJ",
      "strongs": [
        "G5620"
      ],
      "metadata": {
        "src": "1"
      },
      "gematria": {
        "standard": 49,
        "ordinal": 10,
        "reduced": 13
      }
    },
    {
      "position": 3,
      "text": "my",
      "lemma": "strong:G1473 lemma.TR:μου",
      "morph": "robinson:P-1GS",
      "strongs": [
        "G1473"
      ],
      "metadata": {
        "src": "4"
      },
      "gematria": {
        "standard": 38,
        "ordinal": 3,
        "reduced": 11
      }
    },
    {
      "position": 4,
      "text": "bonds",
      "lemma": "strong:G3588 strong:G1199 lemma.TR:τους lemma.TR:δεσμους",
      "morph": "robinson:T-APM robinson:N-APM",
      "strongs": [
        "G3588",
        "G1199"
      ],
      "metadata": {
        "src": "2 3"
      },
      "gematria": {
        "standard": 54,
        "ordinal": 15,
        "reduced": 18
      }
    },
    {
      "position": 5,
      "text": "in",
      "lemma": "strong:G1722 lemma.TR:εν",
      "morph": "robinson:PREP",
      "strongs": [
        "G1722"
      ],
      "metadata": {
        "src": "6"
      },
      "gematria": {
        "standard": 23,
        "ordinal": 3,
        "reduced": 14
      }
    },
    {
      "position": 6,
      "text": "Christ",
      "lemma": "strong:G5547 lemma.TR:χριστω",
      "morph": "robinson:N-DSM",
      "strongs": [
        "G5547"
      ],
      "metadata": {
        "src": "7"
      },
      "gematria": {
        "standard": 77,
        "ordinal": 21,
        "reduced": 32
      }
    },
    {
      "position": 7,
      "text": "are",
      "lemma": "strong:G1096 lemma.TR:γενεσθαι",
      "morph": "robinson:V-2ADN",
      "strongs": [
        "G1096"
      ],
      "metadata": {
        "src": "8"
      },
      "gematria": {
        "standard": 24,
        "ordinal": 6,
        "reduced": 15
      }
    },
    {
      "position": 8,
      "text": "manifest",
      "lemma": "strong:G5318 lemma.TR:φανερους",
      "morph": "robinson:A-APM",
      "strongs": [
        "G5318"
      ],
      "metadata": {
        "src": "5"
      },
      "gematria": {
        "standard": 87,
        "ordinal": 36,
        "reduced": 33
      }
    },
    {
      "position": 9,
      "text": "in",
      "lemma": "strong:G1722 lemma.TR:εν",
      "morph": "robinson:PREP",
      "strongs": [
        "G1722"
      ],
      "metadata": {
        "src": "9"
      },
      "gematria": {
        "standard": 23,
        "ordinal": 3,
        "reduced": 14
      }
    },
    {
      "position": 10,
      "text": "all",
      "lemma": "strong:G3650 lemma.TR:ολω",
      "morph": "robinson:A-DSN",
      "strongs": [
        "G3650"
      ],
      "metadata": {
        "src": "10"
      },
      "gematria": {
        "standard": 25,
        "ordinal": 6,
        "reduced": 7
      }
    },
    {
      "position": 11,
      "text": "the",
      "lemma": "strong:G3588 strong:G4232 lemma.TR:τω lemma.TR:πραιτωριω",
      "morph": "robinson:T-DSN robinson:N-DSN",
      "strongs": [
        "G3588",
        "G4232"
      ],
      "metadata": {
        "src": "11 12"
      },
      "gematria": {
        "standard": 33,
        "ordinal": 6,
        "reduced": 15
      }
    },
    {
      "position": 12,
      "text": "palace,",
      "lemma": "strong:G3588 strong:G4232 lemma.TR:τω lemma.TR:πραιτωριω",
      "morph": "robinson:T-DSN robinson:N-DSN",
      "strongs": [
        "G3588",
        "G4232"
      ],
      "metadata": {
        "src": "11 12"
      },
      "gematria": {
        "standard": 38,
        "ordinal": 21,
        "reduced": 20
      }
    },
    {
      "position": 13,
      "text": "and",
      "lemma": "strong:G2532 lemma.TR:και",
      "morph": "robinson:CONJ",
      "strongs": [
        "G2532"
      ],
      "metadata": {
        "src": "13"
      },
      "gematria": {
        "standard": 19,
        "ordinal": 6,
        "reduced": 10
      }
    },
    {
      "position": 14,
      "text": "in",
      "lemma": "strong:G3062 lemma.TR:λοιποις",
      "morph": "robinson:A-DPM",
      "strongs": [
        "G3062"
      ],
      "metadata": {
        "src": "15",
        "type": "x-split-3070"
      },
      "gematria": {
        "standard": 23,
        "ordinal": 3,
        "reduced": 14
      }
    },
    {
      "position": 15,
      "text": "all",
      "lemma": "strong:G3956 lemma.TR:πασιν",
      "morph": "robinson:A-DPM",
      "strongs": [
        "G3956"
      ],
      "metadata": {
        "src": "16"
      },
      "gematria": {
        "standard": 25,
        "ordinal": 6,
        "reduced": 7
      }
    },
    {
      "position": 16,
      "text": "other",
      "lemma": "strong:G3062 lemma.TR:λοιποις",
      "morph": "robinson:A-DPM",
      "strongs": [
        "G3062"
      ],
      "metadata": {
        "src": "15",
        "type": "x-split-3070"
      },
      "gematria": {
        "standard": 66,
        "ordinal": 15,
        "reduced": 30
      }
    },
    {
      "position": 17,
      "text": "places;",
      "lemma": null,
      "morph": null,
      "metadata": {
        "type": "added"
      },
      "gematria": {
        "standard": 56,
        "ordinal": 21,
        "reduced": 20
      }
    }
  ],
  "gematria": {
    "standard": 694,
    "ordinal": 184,
    "reduced": 280
  }
}