{
  "text": "And it came to pass, that, when Abraham’s servant heard their words, he worshipped the Lord, bowing himself to the earth.",
  "words": [
    {
      "position": 1,
      "text": "And",
      "lemma": "strong:H085",
      "morph": null,
      "strongs": [
        "H85"
      ],
      "gematria": {
        "standard": 19,
        "ordinal": 6,
        "reduced": 10
      }
    },
    {
      "position": 2,
      "text": "it",
      "lemma": "strong:H085",
      "morph": null,
      "strongs": [
        "H85"
      ],
      "gematria": {
        "standard": 29,
        "ordinal": 3,
        "reduced": 11
      }
    },
    {
      "position": 3,
      "text": "came",
      "lemma": "strong:H085",
      "morph": null,
      "strongs": [
        "H85"
      ],
      "gematria": {
        "standard": 22,
        "ordinal": 10,
        "reduced": 13
      }
    },
    {
      "position": 4,
      "text": "to",
      "lemma": "strong:H085",
      "morph": null,
      "strongs": [
        "H85"
      ],
      "gematria": {
        "standard": 35,
        "ordinal": 3,
        "reduced": 8
      }
    },
    {
      "position": 5,
      "text": "pass,",
      "lemma": "strong:H085",
      "morph": null,
      "strongs": [
        "H85"
      ],
      "gematria": {
        "standard": 55,
        "ordinal": 10,
        "reduced": 10
      }
    },
    {
      "position": 6,
      "text": "that,",
      "lemma": "strong:H085",
      "morph": null,
      "strongs": [
        "H85"
      ],
      "gematria": {
        "standard": 49,
        "ordinal": 10,
        "reduced": 13
      }
    },
    {
      "position": 7,
      "text": "when",
      "lemma": "strong:H085",
      "morph": null,
      "strongs": [
        "H85"
      ],
      "gematria": {
        "standard": 50,
        "ordinal": 10,
        "reduced": 23
      }
    },
    {
      "position": 8,
      "text": "Abraham’s",
      "lemma": "strong:H085",
      "morph": null,
      "strongs": [
        "H85"
      ],
      "gematria": {
        "standard": 63,
        "ordinal": 36,
        "reduced": 27
      }
    },
    {
      "position": 9,
      "text": "servant",
      "lemma": "strong:H05650",
      "morph": null,
      "strongs": [
        "H5650"
      ],
      "gematria": {
        "standard": 99,
        "ordinal": 28,
        "reduced": 27
      }
    },
    {
      "position": 10,
      "text": "heard",
      "lemma": "strong:H08085",
      "morph": "strongMorph:TH8804",
      "strongs": [
        "H8085"
      ],
      "gematria": {
        "standard": 36,
        "ordinal": 15,
        "reduced": 27
      }
    },
    {
      "position": 11,
      "text": "their",
      "lemma": "strong:H01697",
      "morph": null,
      "strongs": [
        "H1697"
      ],
      "gematria": {
        "standard": 60,
        "ordinal": 15,
        "reduced": 33
      }
    },
    {
      "position": 12,
      "text": "words,",
      "lemma": "strong:H01697",
      "morph": null,
      "strongs": [
        "H1697"
      ],
      "gematria": {
        "standard": 79,
        "ordinal": 15,
        "reduced": 25
      }
    },
    {
      "position": 13,
      "text": "he",
      "lemma": "strong:H07812",
      "morph": "strongMorph:TH8691",
      "strongs": [
        "H7812"
      ],
      "gematria": {
        "standard": 13,
        "ordinal": 3,
        "reduced": 13
      }
    },
    {
      "position": 14,
      "text": "worshipped",
      "lemma": "strong:H07812",
      "morph": "strongMorph:TH8691",
      "strongs": [
        "H7812"
      ],
      "gematria": {
        "standard": 133,
        "ordinal": 55,
        "reduced": 61
      }
    },
    {
      "position": 15,
      "text": "the",
      "lemma": "strong:H03068",
      "morph": null,
      "strongs": [
        "H3068"
      ],
      "gematria": {
        "standard": 33,
        "ordinal": 6,
        "reduced": 15
      }
    },
    {
      "position": 16,
      "text": "Lord,",
      "lemma": "strong:H03068",
      "morph": null,
      "strongs": [
        "H3068"
      ],
      "gematria": {
        "standard": 49,
        "ordinal": 10,
        "reduced": 22
      }
    },
    {
      "position": 17,
      "text": "bowing himself",
      "lemma": null,
      "morph": null,
      "metadata": {
        "type": "added"
      },
      "gematria": {
        "standard": 142,
        "ordinal": 91,
        "reduced": 70
      }
    },
    {
      "position": 18,
      "text": "to",
      "lemma": "strong:H0776",
      "morph": null,
      "strongs": [
        "H776"
      ],
      "gematria": {
        "standard": 35,
        "ordinal": 3,
        "reduced": 8
      }
    },
    {
      "position": 19,
      "text": "the",
      "lemma": "strong:H0776",
      "morph": null,
      "strongs": [
        "H776"
      ],
      "gematria": {
        "standard": 33,
        "ordinal": 6,
        "reduced": 15
      }
    },
    {
      "position": 20,
      "text": "earth.",
      "lemma": "strong:H0776",
      "morph": null,
      "strongs": [
        "H776"
      ],
      "gematria": {
        "standard": 52,
        "ordinal": 15,
        "reduced": 25
      }
    }
  ],
  "gematria": {
    "standard": 1086,
    "ordinal": 350,
    "reduced": 456
  }
}